git4net/__init__.py
git4net/command_line.py
git4net/complexity.py
git4net/disambiguation.py
git4net/extraction.py
git4net/visualisation.py
git4net-0.0.2.dist-info/LICENSE.txt
git4net-0.0.2.dist-info/METADATA
git4net-0.0.2.dist-info/WHEEL
git4net-0.0.2.dist-info/entry_points.txt
git4net-0.0.2.dist-info/top_level.txt
git4net-0.0.2.dist-info/RECORD
