Metadata-Version: 2.1
Name: git4net
Version: 0.0.2
Summary: My short description for my project.
Home-page: https://github.com/franceme/git4net
Author: Miles Frantz
Author-email: frantzme@vt.edu
License: AGPL-3.0+
Keywords: co-editing,networks,repository,mining,network,analysis
Classifier: Programming Language :: Python
Classifier: Programming Language :: Python :: 3
Classifier: Programming Language :: Python :: 3.8
Requires-Python: >=3.8.0
License-File: LICENSE.txt
Requires-Dist: datasets
Requires-Dist: huggingface-hub
Requires-Dist: PyGithub
Requires-Dist: python-gitlab
Requires-Dist: ruamel.std.zipfile
